bsb_neuron/__init__.py
bsb_neuron/adapter.py
bsb_neuron/cell.py
bsb_neuron/connection.py
bsb_neuron/device.py
bsb_neuron/simulation.py
bsb_neuron/devices/__init__.py
bsb_neuron/devices/current_clamp.py
bsb_neuron/devices/spike_generator.py
bsb_neuron/devices/synapse_recorder.py
bsb_neuron/devices/voltage_clamp.py
bsb_neuron/devices/voltage_recorder.py
bsb_neuron-7.2.1.dist-info/entry_points.txt
bsb_neuron-7.2.1.dist-info/licenses/LICENSE
bsb_neuron-7.2.1.dist-info/WHEEL
bsb_neuron-7.2.1.dist-info/METADATA
bsb_neuron-7.2.1.dist-info/RECORD
